<?xml version='1.0' encoding='utf-8' standalone='yes' ?>
<carrier_config_list>
<carrier_config>
<int name="recipientLimit" value="10" />
<int name="maxImageHeight" value="1944" />
<int name="maxMessageSize" value="1048576" />
<int name="maxImageWidth" value="2592" />
<boolean name="enableSMSDeliveryReports" value="false" />
<boolean name="csp_enabled_bool" value="true" />
<string-array name="cdma_roaming_networks_string_array" num="5">
    <item value="310110" />
    <item value="310140" />
    <item value="310400" />
    <item value="310470" />
    <item value="311170" />
</string-array>
</carrier_config>
</carrier_config_list>
